datapath_tb.v
//=========================================================================
// Name & Email must be EXACTLY as in Gradescope roster!
// Name: Nicole Navarro      
// Email: nnava026@ucr.edu
// 
// Assignment name: Lab 4 Datapath Control Units
// Lab section: 021
// TA: Jincong Lu
// 
// I hereby certify that I have not received assistance on this assignment,
// or used code, from ANY outside source other than the instruction team
// (apart from what was provided in the starter file).
//
//=========================================================================

`timescale 1ns / 1ps

module datapath_tb;
    // Inputs
    reg clk; 
    reg [5:0] instr_op;    
    reg [5:0] instr_field;

    wire [8:0] result;
    wire [3:0] alu_result;

    reg [8:0] R;
    reg [3:0] R_alu;

    // -------------------------------------------------------
    // Setup output file for possible debugging uses
    // -------------------------------------------------------
    initial
    begin
        $dumpfile("lab04.vcd");
        $dumpvars(0);
    end
    
    // ---------------------------------------------------
    // Instantiate the Units Under Test (UUT)
    // --------------------------------------------------- 
    
    initial begin 
        clk = 0;
        forever begin 
            clk = ~clk; #10; 
        end 
    end
     
    integer failedTests = 0;
    integer totalTests = 0;
    initial begin
        // Reset
        @(posedge clk); // Wait for first clock out of reset 
        #10; // Wait 

        // -------------------------------------------------------
        // Test group 1: Control Unit
        // -------------------------------------------------------
        $display("Test Group 1: Testing Control unit... ");

        $write("\tTest Case 1.1: R-format ...");
        totalTests = totalTests + 1;
        // Set inputs
        instr_op = 6'b000000;
        R = { 9'b100100010 }; 
        #100; // Wait
        if (R != result) begin
            $display("failed: Expected: %b, got %b", R, result); 
            failedTests = failedTests + 1;
        end else begin
            $display("passed"); 
        end

        // -------------------------------------------------------
        // More Control Unit tests here
        // -------------------------------------------------------

        $write("\tTest Case 1.2: LW ...");
        totalTests = totalTests + 1;
        // Set inputs
        instr_op = 6'b100011;
        R = { 9'b011110000 }; 
        #100; // Wait
        if (R != result) begin
            $display("failed: Expected: %b, got %b", R, result); 
            failedTests = failedTests + 1;
        end else begin
            $display("passed"); 
        end

        $write("\tTest Case 1.3: SW ...");
        totalTests = totalTests + 1;
        // Set inputs
        instr_op = 6'b101011;
        R = { 9'bX1X001000 }; 
        #100; // Wait
        if (R != result) begin
            $display("failed: Expected: %b, got %b", R, result); 
            failedTests = failedTests + 1;
        end else begin
            $display("passed"); 
        end

        $write("\tTest Case 1.4: BEQ ...");
        totalTests = totalTests + 1;
        // Set inputs
        instr_op = 6'b000100;
        R = { 9'bX0X000101 }; 
        #100; // Wait
        if (R != result) begin
            $display("failed: Expected: %b, got %b", R, result); 
            failedTests = failedTests + 1;
        end else begin
            $display("passed"); 
        end

        //WE HAVE TO FIGURE OUT IMM VALUES
        /*
        $write("\tTest Case 1.5: IMM ...");
        totalTests = totalTests + 1;
        // Set inputs
        instr_op = 6'b001000;
        R = { 9'b }; 
        #100; // Wait
        if (R != result) begin
            $display("failed: Expected: %b, got %b", R, result); 
            failedTests = failedTests + 1;
        end else begin
            $display("passed"); 
        end*/

        // -------------------------------------------------------
        // Test group 2: ALU Control Unit
        // -------------------------------------------------------
        $display("\nTest Group 2: Testing ALU Control unit... ");

        $write("\tTest Case 2.1: R-type (add) ...");
        totalTests = totalTests + 1;
        // Set inputs
        instr_op = 6'b000000;
        instr_field = 6'b100000;
        R_alu = { 4'b0010 }; 
        #100; // Wait
        if (R_alu !== alu_result) begin
            $display("failed: Expected: %b, got %b", R_alu, alu_result); 
            failedTests = failedTests + 1;
        end else begin
            $display("passed"); 
        end

        // -------------------------------------------------------
        // More ALU Control Unit tests jere
        // -------------------------------------------------------

        //Based on the first test, going with the 2nd chart in README
        //Funct field is instr_field
        // instr_op is input op from earlier tests
        //R_alu is referring to ALU select input

        $write("\tTest Case 2.2: R-type (subtract) ...");
        totalTests = totalTests + 1;
        // Set inputs
        instr_op = 6'b000000;
        instr_field = 6'b100010;
        R_alu = { 4'b0110 }; 
        #100; // Wait
        if (R_alu !== alu_result) begin
            $display("failed: Expected: %b, got %b", R_alu, alu_result); 
            failedTests = failedTests + 1;
        end else begin
            $display("passed"); 
        end

        $write("\tTest Case 2.3: R-type (AND) ...");
        totalTests = totalTests + 1;
        // Set inputs
        instr_op = 6'b000000;
        instr_field = 6'b100100;
        R_alu = { 4'b0000 }; 
        #100; // Wait
        if (R_alu !== alu_result) begin
            $display("failed: Expected: %b, got %b", R_alu, alu_result); 
            failedTests = failedTests + 1;
        end else begin
            $display("passed"); 
        end

        $write("\tTest Case 2.4: R-type (OR) ...");
        totalTests = totalTests + 1;
        // Set inputs
        instr_op = 6'b000000;
        instr_field = 6'b100100;
        R_alu = { 4'b0001 }; 
        #100; // Wait
        if (R_alu !== alu_result) begin
            $display("failed: Expected: %b, got %b", R_alu, alu_result); 
            failedTests = failedTests + 1;
        end else begin
            $display("passed"); 
        end

        $write("\tTest Case 2.5: R-type (NOR) ...");
        totalTests = totalTests + 1;
        // Set inputs
        instr_op = 6'b000000;
        instr_field = 6'b100111;
        R_alu = { 4'b1100 }; 
        #100; // Wait
        if (R_alu !== alu_result) begin
            $display("failed: Expected: %b, got %b", R_alu, alu_result); 
            failedTests = failedTests + 1;
        end else begin
            $display("passed"); 
        end

        $write("\tTest Case 2.6: R-type (Set on less than) ...");
        totalTests = totalTests + 1;
        // Set inputs
        instr_op = 6'b000000;
        instr_field = 6'b101010;
        R_alu = { 4'b0111 }; 
        #100; // Wait
        if (R_alu !== alu_result) begin
            $display("failed: Expected: %b, got %b", R_alu, alu_result); 
            failedTests = failedTests + 1;
        end else begin
            $display("passed"); 
        end

        $write("\tTest Case 2.7: LW (load word)...");
        totalTests = totalTests + 1;
        // Set inputs
        instr_op = 6'b100011;
        instr_field = 6'bXXXXXX;
        R_alu = { 4'b0010 }; 
        #100; // Wait
        if (R_alu !== alu_result) begin
            $display("failed: Expected: %b, got %b", R_alu, alu_result); 
            failedTests = failedTests + 1;
        end else begin
            $display("passed"); 
        end

        $write("\tTest Case 2.8: SW (store word) ...");
        totalTests = totalTests + 1;
        // Set inputs
        instr_op = 6'b101011;
        instr_field = 6'bXXXXXX;
        R_alu = { 4'b0010 }; 
        #100; // Wait
        if (R_alu !== alu_result) begin
            $display("failed: Expected: %b, got %b", R_alu, alu_result); 
            failedTests = failedTests + 1;
        end else begin
            $display("passed"); 
        end

        $write("\tTest Case 2.9: BEQ (branch equal) ...");
        totalTests = totalTests + 1;
        // Set inputs
        instr_op = 6'b000100;
        instr_field = 6'bXXXXXX;
        R_alu = { 4'b0010 }; 
        #100; // Wait
        if (R_alu !== alu_result) begin
            $display("failed: Expected: %b, got %b", R_alu, alu_result); 
            failedTests = failedTests + 1;
        end else begin
            $display("passed"); 
        end

        // --------------------------------------------------------------
        // End testing
        // --------------------------------------------------------------
        $write("\n--------------------------------------------------------------");
        $write("\nTesting complete\nPassed %0d / %0d tests",totalTests-failedTests,totalTests);
        $write("\n--------------------------------------------------------------\n");
        $finish();
    end
endmodule

controlUnit.v
//=========================================================================
// Name & Email must be EXACTLY as in Gradescope roster!
// Name: Nicole Navarro  
// Email: nnava026@ucr.edu
// 
// Assignment name: Lab 4 Datapath Control units
// Lab section: 021
// TA: Jincong Lu
// 
// I hereby certify that I have not received assistance on this assignment,
// or used code, from ANY outside source other than the instruction team
// (apart from what was provided in the starter file).
//
//=========================================================================

module controlUnit  (
    input  wire [5:0] instr_op, 
    output wire       reg_dst,   
    output wire       branch,     
    output wire       mem_read,  
    output wire       mem_to_reg,
    output wire [1:0] alu_op,        
    output wire       mem_write, 
    output wire       alu_src,    
    output wire       reg_write
    );

// ------------------------------
// Insert your solution below
// ------------------------------ 
    
    reg reg_dst_reg; 
    reg branch_reg;
    reg mem_read_reg;
    reg mem_to_reg_reg;
    reg alu_op_reg;
    reg mem_write_reg;
    reg alu_src_reg;
    reg reg_write_reg;

    assign reg_st = reg_dst_reg;
    assign branch = branch_reg;
    assign mem_read = mem_read_reg;
    assign mem_to_reg = mem_to_reg_reg;
    assign alu_op = alu_op_reg;
    assign mem_write = mem_write_reg;
    assign alu_src = alu_src_reg;
    assign reg_write = reg_write_reg;

    always @(*) begin
        casex(instr_op)
            6'b000000: begin
                reg_dst_reg = 1'b1;
                branch_reg = 1'b0;
                mem_read_reg = 1'b0;
                mem_to_reg_reg = 1'b0;
                alu_op_reg = 2'b10;
                mem_write_reg = 1'b0;
                alu_src_reg = 1'b0;
                reg_write_reg = 1'b1;
            end
            6'b100011: begin
                reg_dst_reg = 1'b0;
                branch_reg = 1'b0;
                mem_read_reg = 1'b1;
                mem_to_reg_reg = 1'b1;
                alu_op_reg = 2'b00;
                mem_write_reg = 1'b0;
                alu_src_reg = 1'b1;
                reg_write_reg = 1'b1;
            end
            6'b101011: begin
                reg_dst_reg = 1'bX;
                branch_reg = 1'b0;
                mem_read_reg = 1'b0;
                mem_to_reg_reg = 1'bX;
                alu_op_reg = 2'b00;
                mem_write_reg = 1'b1;
                alu_src_reg = 1'b1;
                reg_write_reg = 1'b1;
            end
            6'b000100: begin
                reg_dst_reg = 1'bX;
                branch_reg = 1'b1;
                mem_read_reg = 1'b0;
                mem_to_reg_reg = 1'bX;
                alu_op_reg = 2'b01;
                mem_write_reg = 1'b0;
                alu_src_reg = 1'b0;
                reg_write_reg = 1'b0;
            end
            6'b001000: begin
                reg_dst_reg = 1'b1;
                branch_reg = 1'b0;
                mem_read_reg = 1'b0;
                mem_to_reg_reg = 1'b0;
                alu_op_reg = 2'b10;
                mem_write_reg = 1'b0;
                alu_src_reg = 1'b1;
                reg_write_reg = 1'b1;
            end
        endcase

    end


endmodule

aluControlUnit.v
//=========================================================================
// Name & Email must be EXACTLY as in Gradescope roster!
// Name: Nicole Navarro 
// Email: nnava026@ucr.edu
// 
// Assignment name: Lab 4 Datapath Control Units 
// Lab section: 021
// TA: Jincong Lu
// 
// I hereby certify that I have not received assistance on this assignment,
// or used code, from ANY outside source other than the instruction team
// (apart from what was provided in the starter file).
//
//=========================================================================

module aluControlUnit (
    input  wire [1:0] alu_op, 
    input  wire [5:0] instruction_5_0, 
    output wire [3:0] alu_out
    );

// ------------------------------
// Insert your solution below
// ------------------------------ 

    reg alu_out_reg;

    assign alu_out = alu_out_reg;

    controlUnit #() get_op(
        .instr_op(instruction_5_0),
        .alu_op(alu_op));

    always @(*) begin
        casex({alu_op,instruction_5_0})
            8'b00XXXXXX: begin
                alu_out_reg = 4'b0010;
            end
            8'bX1XXXXXX: begin
                alu_out_reg = 4'b0110;
            end
            8'b1XXX0000:begin
                alu_out_reg = 4'b0010;
            end
            8'b1XXX0000: begin
                alu_out_reg = 4'b0110;
            end
            8'b1XXX0010: begin
                alu_out_reg = 4'b0000;
            end
            8'b1XXX0100:begin
                alu_out_reg = 4'b0001;
            end
            8'b1XXX1010:begin
                alu_out_reg = 4'b0111;
            end
            8'b1XXX0111:begin
                alu_out_reg = 4'b1100;
            end
        endcase
    end


endmodule

lab04.vcd
$date
	Wed Mar  1 00:49:21 2023
$end
$version
	Icarus Verilog
$end
$timescale
	1ps
$end
$scope module aluControlUnit $end
$var wire 6 ! instruction_5_0 [5:0] $end
$var wire 4 " alu_out [3:0] $end
$var wire 2 # alu_op [1:0] $end
$var reg 1 $ alu_out_reg $end
$scope module get_op $end
$var wire 1 % alu_src $end
$var wire 1 & branch $end
$var wire 6 ' instr_op [5:0] $end
$var wire 1 ( mem_read $end
$var wire 1 ) mem_to_reg $end
$var wire 1 * mem_write $end
$var wire 1 + reg_dst $end
$var wire 1 , reg_st $end
$var wire 1 - reg_write $end
$var wire 2 . alu_op [1:0] $end
$var reg 1 / alu_op_reg $end
$var reg 1 0 alu_src_reg $end
$var reg 1 1 branch_reg $end
$var reg 1 2 mem_read_reg $end
$var reg 1 3 mem_to_reg_reg $end
$var reg 1 4 mem_write_reg $end
$var reg 1 5 reg_dst_reg $end
$var reg 1 6 reg_write_reg $end
$upscope $end
$upscope $end
$scope module datapath_tb $end
$var wire 4 7 alu_result [3:0] $end
$var wire 9 8 result [8:0] $end
$var reg 9 9 R [8:0] $end
$var reg 4 : R_alu [3:0] $end
$var reg 1 ; clk $end
$var reg 6 < instr_field [5:0] $end
$var reg 6 = instr_op [5:0] $end
$var integer 32 > failedTests [31:0] $end
$var integer 32 ? totalTests [31:0] $end
$upscope $end
$enddefinitions $end
#0
$dumpvars
b0 ?
b0 >
bx =
bx <
1;
bx :
bx 9
bz 8
bz 7
16
15
04
03
02
01
00
0/
b0 .
1-
1,
z+
0*
0)
0(
bz '
0&
0%
0$
b0 #
b0 "
bz !
$end
#10000
0;
#20000
1;
#30000
b100100010 9
b0 =
b1 ?
0;
#40000
1;
#50000
0;
#60000
1;
#70000
0;
#80000
1;
#90000
0;
#100000
1;
#110000
0;
#120000
1;
#130000
0;
b11110000 9
b100011 =
b10 ?
#140000
1;
#150000
0;
#160000
1;
#170000
0;
#180000
1;
#190000
0;
#200000
1;
#210000
0;
#220000
1;
#230000
0;
bx1x001000 9
b101011 =
b11 ?
#240000
1;
#250000
0;
#260000
1;
#270000
0;
#280000
1;
#290000
0;
#300000
1;
#310000
0;
#320000
1;
#330000
0;
bx0x000101 9
b100 =
b100 ?
#340000
1;
#350000
0;
#360000
1;
#370000
0;
#380000
1;
#390000
0;
#400000
1;
#410000
0;
#420000
1;
#430000
0;
b10 :
b100000 <
b0 =
b101 ?
#440000
1;
#450000
0;
#460000
1;
#470000
0;
#480000
1;
#490000
0;
#500000
1;
#510000
0;
#520000
1;
#530000
0;
b110 :
b100010 <
b110 ?
b1 >
#540000
1;
#550000
0;
#560000
1;
#570000
0;
#580000
1;
#590000
0;
#600000
1;
#610000
0;
#620000
1;
#630000
0;
b0 :
b100100 <
b111 ?
b10 >
#640000
1;
#650000
0;
#660000
1;
#670000
0;
#680000
1;
#690000
0;
#700000
1;
#710000
0;
#720000
1;
#730000
0;
b1 :
b1000 ?
b11 >
#740000
1;
#750000
0;
#760000
1;
#770000
0;
#780000
1;
#790000
0;
#800000
1;
#810000
0;
#820000
1;
#830000
0;
b1100 :
b100111 <
b1001 ?
b100 >
#840000
1;
#850000
0;
#860000
1;
#870000
0;
#880000
1;
#890000
0;
#900000
1;
#910000
0;
#920000
1;
#930000
0;
b111 :
b101010 <
b1010 ?
b101 >
#940000
1;
#950000
0;
#960000
1;
#970000
0;
#980000
1;
#990000
0;
#1000000
1;
#1010000
0;
#1020000
1;
#1030000
0;
b10 :
bx <
b100011 =
b1011 ?
b110 >
#1040000
1;
#1050000
0;
#1060000
1;
#1070000
0;
#1080000
1;
#1090000
0;
#1100000
1;
#1110000
0;
#1120000
1;
#1130000
0;
b101011 =
b1100 ?
b111 >
#1140000
1;
#1150000
0;
#1160000
1;
#1170000
0;
#1180000
1;
#1190000
0;
#1200000
1;
#1210000
0;
#1220000
1;
#1230000
0;
b100 =
b1101 ?
b1000 >
#1240000
1;
#1250000
0;
#1260000
1;
#1270000
0;
#1280000
1;
#1290000
0;
#1300000
1;
#1310000
0;
#1320000
1;
#1330000
0;
b1001 >
